odoo/addons/hr_expense_payment/README.rst
odoo/addons/hr_expense_payment/__init__.py
odoo/addons/hr_expense_payment/__manifest__.py
odoo/addons/hr_expense_payment/hooks.py
odoo/addons/hr_expense_payment/i18n/hr_expense_payment.pot
odoo/addons/hr_expense_payment/models/__init__.py
odoo/addons/hr_expense_payment/models/account_payment.py
odoo/addons/hr_expense_payment/models/hr_expense_sheet.py
odoo/addons/hr_expense_payment/readme/CONTRIBUTORS.rst
odoo/addons/hr_expense_payment/readme/DESCRIPTION.rst
odoo/addons/hr_expense_payment/static/description/icon.png
odoo/addons/hr_expense_payment/static/description/index.html
odoo/addons/hr_expense_payment/tests/__init__.py
odoo/addons/hr_expense_payment/tests/test_hr_expense_payment.py
odoo/addons/hr_expense_payment/wizard/__init__.py
odoo/addons/hr_expense_payment/wizard/account_payment_register.py
odoo14_addon_hr_expense_payment-14.0.1.0.1.dist-info/METADATA
odoo14_addon_hr_expense_payment-14.0.1.0.1.dist-info/WHEEL
odoo14_addon_hr_expense_payment-14.0.1.0.1.dist-info/top_level.txt
odoo14_addon_hr_expense_payment-14.0.1.0.1.dist-info/RECORD
